ap_utilities/bookkeeping/bkk_checker.py
ap_utilities/bookkeeping/sample_config.py
ap_utilities/decays/utilities.py
ap_utilities/io/utilities.py
ap_utilities/logfiles/log_info.py
ap_utilities/logging/log_store.py
ap_utilities/mcdecay/nicknames.py
ap_utilities-0.3.0.data/scripts/dirac_shell
ap_utilities-0.3.0.data/scripts/ganga_shell
ap_utilities_data/analyses/analyses.yaml
ap_utilities_data/analyses/by_priority.yaml
ap_utilities_data/naming/evt_dec.yaml
ap_utilities_data/naming/evt_form.yaml
ap_utilities_data/naming/evt_name.yaml
ap_utilities_data/naming/evt_old_name.yaml
ap_utilities_data/naming/form_evt.yaml
ap_utilities_data/naming/lower_original.yaml
ap_utilities_data/naming/name_evt.yaml
ap_utilities_data/naming/ntuple_scheme.yaml
ap_utilities_data/naming/old_name_evt.yaml
ap_utilities_data/production/stage0.yaml
ap_utilities_data/samples/2024_sim10d.yaml
ap_utilities_data/samples/2024_sim10f.yaml
ap_utilities_data/tests/nick_evt.yaml
ap_utilities_data/tests/rd_samples.yaml
ap_utilities_data/validation/05_09_2024.yaml
ap_utilities_scripts/analyze_samples.py
ap_utilities_scripts/check_production.py
ap_utilities_scripts/check_samples.py
ap_utilities_scripts/dirac_shell
ap_utilities_scripts/find_in_ap.py
ap_utilities_scripts/ganga_shell
ap_utilities_scripts/list_ap_samples.py
ap_utilities_scripts/make_fields.py
ap_utilities_scripts/make_name_evt.py
ap_utilities_scripts/make_samples_table.py
ap_utilities_scripts/samples_to_filter.py
ap_utilities_scripts/update_decinfo.py
ap_utilities_scripts/update_sample_naming.py
ap_utilities_scripts/validate_ap_tuples.py
ap_utilities-0.3.0.dist-info/METADATA
ap_utilities-0.3.0.dist-info/WHEEL
ap_utilities-0.3.0.dist-info/entry_points.txt
ap_utilities-0.3.0.dist-info/top_level.txt
ap_utilities-0.3.0.dist-info/RECORD
