Metadata-Version: 2.4
Name: ap_utilities
Version: 0.3.0
Summary: Utilities needed for analysis productions in LHCb
Requires-Dist: apd
Requires-Dist: PyYAML
Requires-Dist: tqdm
Requires-Dist: omegaconf
Requires-Dist: logzero
Provides-Extra: dev
Requires-Dist: pytest; extra == "dev"
